{"data": [{"units": "celsius", "dt": "2024-12-22T20:11:58Z", "name": "temperature", "value": 24.2}, {"units": "percent", "dt": "2024-12-22T20:11:58Z", "name": "humidity", "value": 47.8}, {"units": "pascal", "dt": "2024-12-22T20:11:58Z", "name": "pressure", "value": 96572.6}, {"units": "decibel", "dt": "2024-12-22T20:11:58Z", "name": "sound", "value": 54.8}, {"units": "percent", "dt": "2024-12-22T20:11:58Z", "name": "luminosity", "value": 7.1}, {"units": "celsius", "dt": "2024-12-22T20:24:34Z", "name": "temperature", "value": 28.2}, {"units": "percent", "dt": "2024-12-22T20:24:34Z", "name": "humidity", "value": 47.7}, {"units": "pascal", "dt": "2024-12-22T20:24:34Z", "name": "pressure", "value": 96531.3}, {"units": "decibel", "dt": "2024-12-22T20:24:34Z", "name": "sound", "value": 54.4}, {"units": "percent", "dt": "2024-12-22T20:24:34Z", "name": "luminosity", "value": 7.0}, {"units": "celsius", "dt": "2024-12-22T20:26:34Z", "name": "temperature", "value": 28.4}, {"units": "percent", "dt": "2024-12-22T20:26:34Z", "name": "humidity", "value": 47.6}, {"units": "pascal", "dt": "2024-12-22T20:26:34Z", "name": "pressure", "value": 96520.9}, {"units": "decibel", "dt": "2024-12-22T20:26:34Z", "name": "sound", "value": 57.8}, {"units": "percent", "dt": "2024-12-22T20:26:34Z", "name": "luminosity", "value": 6.9}, {"units": "celsius", "dt": "2024-12-22T20:26:57Z", "name": "temperature", "value": 28.5}, {"units": "percent", "dt": "2024-12-22T20:26:57Z", "name": "humidity", "value": 47.6}, {"units": "pascal", "dt": "2024-12-22T20:26:57Z", "name": "pressure", "value": 96519.4}, {"units": "decibel", "dt": "2024-12-22T20:26:57Z", "name": "sound", "value": 52.5}, {"units": "percent", "dt": "2024-12-22T20:26:57Z", "name": "luminosity", "value": 7.0}, {"units": "celsius", "dt": "2024-12-22T20:30:07Z", "name": "temperature", "value": 28.7}, {"units": "percent", "dt": "2024-12-22T20:30:07Z", "name": "humidity", "value": 47.6}, {"units": "pascal", "dt": "2024-12-22T20:30:07Z", "name": "pressure", "value": 96526.6}, {"units": "decibel", "dt": "2024-12-22T20:30:07Z", "name": "sound", "value": 57.1}, {"units": "percent", "dt": "2024-12-22T20:30:07Z", "name": "luminosity", "value": 7.0}, {"units": "celsius", "dt": "2024-12-22T20:30:24Z", "name": "temperature", "value": 28.7}, {"units": "percent", "dt": "2024-12-22T20:30:24Z", "name": "humidity", "value": 47.6}, {"units": "pascal", "dt": "2024-12-22T20:30:24Z", "name": "pressure", "value": 96522.1}, {"units": "decibel", "dt": "2024-12-22T20:30:24Z", "name": "sound", "value": 57.4}, {"units": "percent", "dt": "2024-12-22T20:30:24Z", "name": "luminosity", "value": 7.0}, {"units": "celsius", "dt": "2024-12-22T20:35:15Z", "name": "temperature", "value": 28.9}, {"units": "percent", "dt": "2024-12-22T20:35:15Z", "name": "humidity", "value": 47.5}, {"units": "pascal", "dt": "2024-12-22T20:35:15Z", "name": "pressure", "value": 96518.1}, {"units": "decibel", "dt": "2024-12-22T20:35:16Z", "name": "sound", "value": 50.6}, {"units": "percent", "dt": "2024-12-22T20:35:16Z", "name": "luminosity", "value": 6.9}, {"units": "celsius", "dt": "2024-12-22T20:36:09Z", "name": "temperature", "value": 28.9}, {"units": "percent", "dt": "2024-12-22T20:36:09Z", "name": "humidity", "value": 47.4}, {"units": "pascal", "dt": "2024-12-22T20:36:09Z", "name": "pressure", "value": 96514.8}, {"units": "decibel", "dt": "2024-12-22T20:36:09Z", "name": "sound", "value": 50.7}, {"units": "percent", "dt": "2024-12-22T20:36:09Z", "name": "luminosity", "value": 6.9}]}